vxci/__init__.py
vxci/builders.py
vxci/checkers.py
vxci/common.py
vxci/coverage.py
vxci/errors.py
vxci/get_addons.py
vxci/image.py
vxci/tools_test.py
vxci/commands/__init__.py
vxci/commands/command.py
vxci/templates/coverage.css
vxci/templates/coveragerc
vxci-0.0.44.dist-info/licenses/AUTHORS.rst
vxci-0.0.44.dist-info/licenses/LICENSE
vxci-0.0.44.dist-info/METADATA
vxci-0.0.44.dist-info/WHEEL
vxci-0.0.44.dist-info/entry_points.txt
vxci-0.0.44.dist-info/top_level.txt
vxci-0.0.44.dist-info/RECORD
